auto_generation_pytest/__init__.py
auto_generation_pytest/cli.py
auto_generation_pytest/combination/__init__.py
auto_generation_pytest/combination/combination_case.py
auto_generation_pytest/combination/combination_inhert.py
auto_generation_pytest/create.py
auto_generation_pytest/demo/demo_grpc.json
auto_generation_pytest/demo/demo_http.json
auto_generation_pytest/get_case.py
auto_generation_pytest/grpcrequests.py
auto_generation_pytest/httprequests.py
auto_generation_pytest/inhert.py
auto_generation_pytest/plugins/pytest_mat.py
auto_generation_pytest/proxy/__init__.py
auto_generation_pytest/proxy/dump.py
auto_generation_pytest/proxy/res_filter.py
auto_generation_pytest/proxy/save.py
auto_generation_pytest/template.py
auto_generation_pytest/utlis.py
auto_generation_pytest-1.0.10.dist-info/entry_points.txt
auto_generation_pytest-1.0.10.dist-info/WHEEL
auto_generation_pytest-1.0.10.dist-info/METADATA
auto_generation_pytest-1.0.10.dist-info/RECORD
