Metadata-Version: 2.1
Name: auto-generation-pytest
Version: 1.0.10
Summary: auto_generation_pytest
Author: moku27
Author-email: xieshi@forchange.tech
Requires-Python: >=3.7,<4.0
Classifier: Programming Language :: Python :: 3
Classifier: Programming Language :: Python :: 3.7
Classifier: Programming Language :: Python :: 3.8
Requires-Dist: PyYaml (>=5.3.1,<6.0.0)
Requires-Dist: allpairspy (>=2.5.0,<3.0.0)
Requires-Dist: allure-pytest (>=2.8.16,<3.0.0)
Requires-Dist: grpcio (>=1.30.0,<2.0.0)
Requires-Dist: grpcio-tools (>=1.30.0,<2.0.0)
Requires-Dist: json_diff
Requires-Dist: mitmproxy
Requires-Dist: pytest (>=5.4.3,<6.0.0)
Requires-Dist: pytest_dependency
Requires-Dist: python-dotenv (>=0.14.0,<0.15.0)
Requires-Dist: requests (>=2.24.0,<3.0.0)
